[
  {
    "file": "music/heat-death/low-tone.ogg",
    "bytes": 300990,
    "probe": {
      "ok": true,
      "durationSeconds": 90,
      "sampleRate": 48000,
      "channels": 2
    },
    "guessedMatrixId": "music-heat-death-low-tone",
    "guessedTargetPath": "music/heat-death/low-tone.ogg",
    "importStatus": "candidate-only"
  },
  {
    "file": "music/heat-death/vanishing-texture.ogg",
    "bytes": 1508678,
    "probe": {
      "ok": true,
      "durationSeconds": 90,
      "sampleRate": 48000,
      "channels": 2
    },
    "guessedMatrixId": "music-heat-death-vanishing-texture",
    "guessedTargetPath": "music/heat-death/vanishing-texture.ogg",
    "importStatus": "candidate-only"
  },
  {
    "file": "music/stellar/bass.ogg",
    "bytes": 178352,
    "probe": {
      "ok": true,
      "durationSeconds": 32,
      "sampleRate": 48000,
      "channels": 2
    },
    "guessedMatrixId": "music-stellar-bass",
    "guessedTargetPath": "music/stellar/bass.ogg",
    "importStatus": "candidate-only"
  },
  {
    "file": "music/stellar/danger.ogg",
    "bytes": 747340,
    "probe": {
      "ok": true,
      "durationSeconds": 32,
      "sampleRate": 48000,
      "channels": 2
    },
    "guessedMatrixId": "music-stellar-danger",
    "guessedTargetPath": "music/stellar/danger.ogg",
    "importStatus": "candidate-only"
  },
  {
    "file": "music/stellar/motion.ogg",
    "bytes": 369889,
    "probe": {
      "ok": true,
      "durationSeconds": 32,
      "sampleRate": 48000,
      "channels": 2
    },
    "guessedMatrixId": "music-stellar-motion",
    "guessedTargetPath": "music/stellar/motion.ogg",
    "importStatus": "candidate-only"
  },
  {
    "file": "music/stellar/pulse.ogg",
    "bytes": 811535,
    "probe": {
      "ok": true,
      "durationSeconds": 32,
      "sampleRate": 48000,
      "channels": 2
    },
    "guessedMatrixId": "music-stellar-pulse",
    "guessedTargetPath": "music/stellar/pulse.ogg",
    "importStatus": "candidate-only"
  },
  {
    "file": "sfx/damage-hit/damage-hit-01.ogg",
    "bytes": 16712,
    "probe": {
      "ok": true,
      "durationSeconds": 0.72,
      "sampleRate": 48000,
      "channels": 2
    },
    "guessedMatrixId": "sfx-damagehit-01",
    "guessedTargetPath": "sfx/damage-hit/damage-hit-01.ogg",
    "importStatus": "candidate-only"
  },
  {
    "file": "sfx/damage-hit/damage-hit-02.ogg",
    "bytes": 16793,
    "probe": {
      "ok": true,
      "durationSeconds": 0.72,
      "sampleRate": 48000,
      "channels": 2
    },
    "guessedMatrixId": "sfx-damagehit-02",
    "guessedTargetPath": "sfx/damage-hit/damage-hit-02.ogg",
    "importStatus": "candidate-only"
  },
  {
    "file": "sfx/damage-hit/damage-hit-03.ogg",
    "bytes": 16867,
    "probe": {
      "ok": true,
      "durationSeconds": 0.72,
      "sampleRate": 48000,
      "channels": 2
    },
    "guessedMatrixId": "sfx-damagehit-03",
    "guessedTargetPath": "sfx/damage-hit/damage-hit-03.ogg",
    "importStatus": "candidate-only"
  },
  {
    "file": "sfx/damage-hit/damage-hit-04.ogg",
    "bytes": 17063,
    "probe": {
      "ok": true,
      "durationSeconds": 0.72,
      "sampleRate": 48000,
      "channels": 2
    },
    "guessedMatrixId": "sfx-damagehit-04",
    "guessedTargetPath": "sfx/damage-hit/damage-hit-04.ogg",
    "importStatus": "candidate-only"
  },
  {
    "file": "sfx/damage-hit/damage-hit-05.ogg",
    "bytes": 17099,
    "probe": {
      "ok": true,
      "durationSeconds": 0.72,
      "sampleRate": 48000,
      "channels": 2
    },
    "guessedMatrixId": "sfx-damagehit-05",
    "guessedTargetPath": "sfx/damage-hit/damage-hit-05.ogg",
    "importStatus": "candidate-only"
  },
  {
    "file": "sfx/death/death-absorbed-01.ogg",
    "bytes": 62118,
    "probe": {
      "ok": true,
      "durationSeconds": 2.5,
      "sampleRate": 48000,
      "channels": 2
    },
    "guessedMatrixId": "sfx-death-01",
    "guessedTargetPath": "sfx/death/death-absorbed-01.ogg",
    "importStatus": "candidate-only"
  },
  {
    "file": "sfx/death/death-absorbed-02.ogg",
    "bytes": 62264,
    "probe": {
      "ok": true,
      "durationSeconds": 2.5,
      "sampleRate": 48000,
      "channels": 2
    },
    "guessedMatrixId": "sfx-death-02",
    "guessedTargetPath": "sfx/death/death-absorbed-02.ogg",
    "importStatus": "candidate-only"
  },
  {
    "file": "sfx/gate-miss/gate-miss-01.ogg",
    "bytes": 6948,
    "probe": {
      "ok": true,
      "durationSeconds": 0.36,
      "sampleRate": 48000,
      "channels": 2
    },
    "guessedMatrixId": "sfx-gatemiss-01",
    "guessedTargetPath": "sfx/gate-miss/gate-miss-01.ogg",
    "importStatus": "candidate-only"
  },
  {
    "file": "sfx/gate-miss/gate-miss-02.ogg",
    "bytes": 6977,
    "probe": {
      "ok": true,
      "durationSeconds": 0.36,
      "sampleRate": 48000,
      "channels": 2
    },
    "guessedMatrixId": "sfx-gatemiss-02",
    "guessedTargetPath": "sfx/gate-miss/gate-miss-02.ogg",
    "importStatus": "candidate-only"
  },
  {
    "file": "sfx/gate-miss/gate-miss-03.ogg",
    "bytes": 6888,
    "probe": {
      "ok": true,
      "durationSeconds": 0.36,
      "sampleRate": 48000,
      "channels": 2
    },
    "guessedMatrixId": "sfx-gatemiss-03",
    "guessedTargetPath": "sfx/gate-miss/gate-miss-03.ogg",
    "importStatus": "candidate-only"
  },
  {
    "file": "sfx/gravity-well-whoosh/gravity-well-whoosh-01.ogg",
    "bytes": 39680,
    "probe": {
      "ok": true,
      "durationSeconds": 1.12,
      "sampleRate": 48000,
      "channels": 2
    },
    "guessedMatrixId": "sfx-gravitywellwhoosh-01",
    "guessedTargetPath": "sfx/gravity-well-whoosh/gravity-well-whoosh-01.ogg",
    "importStatus": "candidate-only"
  },
  {
    "file": "sfx/gravity-well-whoosh/gravity-well-whoosh-02.ogg",
    "bytes": 39645,
    "probe": {
      "ok": true,
      "durationSeconds": 1.12,
      "sampleRate": 48000,
      "channels": 2
    },
    "guessedMatrixId": "sfx-gravitywellwhoosh-02",
    "guessedTargetPath": "sfx/gravity-well-whoosh/gravity-well-whoosh-02.ogg",
    "importStatus": "candidate-only"
  },
  {
    "file": "sfx/gravity-well-whoosh/gravity-well-whoosh-03.ogg",
    "bytes": 39300,
    "probe": {
      "ok": true,
      "durationSeconds": 1.12,
      "sampleRate": 48000,
      "channels": 2
    },
    "guessedMatrixId": "sfx-gravitywellwhoosh-03",
    "guessedTargetPath": "sfx/gravity-well-whoosh/gravity-well-whoosh-03.ogg",
    "importStatus": "candidate-only"
  },
  {
    "file": "sfx/gravity-well-whoosh/gravity-well-whoosh-04.ogg",
    "bytes": 39359,
    "probe": {
      "ok": true,
      "durationSeconds": 1.12,
      "sampleRate": 48000,
      "channels": 2
    },
    "guessedMatrixId": "sfx-gravitywellwhoosh-04",
    "guessedTargetPath": "sfx/gravity-well-whoosh/gravity-well-whoosh-04.ogg",
    "importStatus": "candidate-only"
  },
  {
    "file": "sfx/hazard-whoosh/hazard-whoosh-01.ogg",
    "bytes": 35342,
    "probe": {
      "ok": true,
      "durationSeconds": 0.72,
      "sampleRate": 48000,
      "channels": 2
    },
    "guessedMatrixId": "sfx-hazardwhoosh-01",
    "guessedTargetPath": "sfx/hazard-whoosh/hazard-whoosh-01.ogg",
    "importStatus": "candidate-only"
  },
  {
    "file": "sfx/hazard-whoosh/hazard-whoosh-02.ogg",
    "bytes": 35176,
    "probe": {
      "ok": true,
      "durationSeconds": 0.72,
      "sampleRate": 48000,
      "channels": 2
    },
    "guessedMatrixId": "sfx-hazardwhoosh-02",
    "guessedTargetPath": "sfx/hazard-whoosh/hazard-whoosh-02.ogg",
    "importStatus": "candidate-only"
  },
  {
    "file": "sfx/hazard-whoosh/hazard-whoosh-03.ogg",
    "bytes": 35362,
    "probe": {
      "ok": true,
      "durationSeconds": 0.72,
      "sampleRate": 48000,
      "channels": 2
    },
    "guessedMatrixId": "sfx-hazardwhoosh-03",
    "guessedTargetPath": "sfx/hazard-whoosh/hazard-whoosh-03.ogg",
    "importStatus": "candidate-only"
  },
  {
    "file": "sfx/hazard-whoosh/hazard-whoosh-04.ogg",
    "bytes": 35360,
    "probe": {
      "ok": true,
      "durationSeconds": 0.72,
      "sampleRate": 48000,
      "channels": 2
    },
    "guessedMatrixId": "sfx-hazardwhoosh-04",
    "guessedTargetPath": "sfx/hazard-whoosh/hazard-whoosh-04.ogg",
    "importStatus": "candidate-only"
  },
  {
    "file": "sfx/hazard-whoosh/hazard-whoosh-05.ogg",
    "bytes": 35420,
    "probe": {
      "ok": true,
      "durationSeconds": 0.72,
      "sampleRate": 48000,
      "channels": 2
    },
    "guessedMatrixId": "sfx-hazardwhoosh-05",
    "guessedTargetPath": "sfx/hazard-whoosh/hazard-whoosh-05.ogg",
    "importStatus": "candidate-only"
  },
  {
    "file": "sfx/hazard-whoosh/hazard-whoosh-06.ogg",
    "bytes": 35504,
    "probe": {
      "ok": true,
      "durationSeconds": 0.72,
      "sampleRate": 48000,
      "channels": 2
    },
    "guessedMatrixId": "sfx-hazardwhoosh-06",
    "guessedTargetPath": "sfx/hazard-whoosh/hazard-whoosh-06.ogg",
    "importStatus": "candidate-only"
  },
  {
    "file": "sfx/line-gate/line-gate-01.ogg",
    "bytes": 6413,
    "probe": {
      "ok": true,
      "durationSeconds": 0.330667,
      "sampleRate": 48000,
      "channels": 2
    },
    "guessedMatrixId": "sfx-linegate-01",
    "guessedTargetPath": "sfx/line-gate/line-gate-01.ogg",
    "importStatus": "candidate-only"
  },
  {
    "file": "sfx/line-gate/line-gate-02.ogg",
    "bytes": 6399,
    "probe": {
      "ok": true,
      "durationSeconds": 0.330667,
      "sampleRate": 48000,
      "channels": 2
    },
    "guessedMatrixId": "sfx-linegate-02",
    "guessedTargetPath": "sfx/line-gate/line-gate-02.ogg",
    "importStatus": "candidate-only"
  },
  {
    "file": "sfx/line-gate/line-gate-03.ogg",
    "bytes": 6521,
    "probe": {
      "ok": true,
      "durationSeconds": 0.330667,
      "sampleRate": 48000,
      "channels": 2
    },
    "guessedMatrixId": "sfx-linegate-03",
    "guessedTargetPath": "sfx/line-gate/line-gate-03.ogg",
    "importStatus": "candidate-only"
  },
  {
    "file": "sfx/line-gate/line-gate-04.ogg",
    "bytes": 6655,
    "probe": {
      "ok": true,
      "durationSeconds": 0.330667,
      "sampleRate": 48000,
      "channels": 2
    },
    "guessedMatrixId": "sfx-linegate-04",
    "guessedTargetPath": "sfx/line-gate/line-gate-04.ogg",
    "importStatus": "candidate-only"
  },
  {
    "file": "sfx/line-gate/line-gate-05.ogg",
    "bytes": 6717,
    "probe": {
      "ok": true,
      "durationSeconds": 0.330667,
      "sampleRate": 48000,
      "channels": 2
    },
    "guessedMatrixId": "sfx-linegate-05",
    "guessedTargetPath": "sfx/line-gate/line-gate-05.ogg",
    "importStatus": "candidate-only"
  },
  {
    "file": "sfx/line-gate/line-gate-06.ogg",
    "bytes": 6954,
    "probe": {
      "ok": true,
      "durationSeconds": 0.330667,
      "sampleRate": 48000,
      "channels": 2
    },
    "guessedMatrixId": "sfx-linegate-06",
    "guessedTargetPath": "sfx/line-gate/line-gate-06.ogg",
    "importStatus": "candidate-only"
  },
  {
    "file": "sfx/rail-scrape/rail-scrape-01.ogg",
    "bytes": 29616,
    "probe": {
      "ok": true,
      "durationSeconds": 0.52,
      "sampleRate": 48000,
      "channels": 2
    },
    "guessedMatrixId": "sfx-railscrape-01",
    "guessedTargetPath": "sfx/rail-scrape/rail-scrape-01.ogg",
    "importStatus": "candidate-only"
  },
  {
    "file": "sfx/rail-scrape/rail-scrape-02.ogg",
    "bytes": 29553,
    "probe": {
      "ok": true,
      "durationSeconds": 0.52,
      "sampleRate": 48000,
      "channels": 2
    },
    "guessedMatrixId": "sfx-railscrape-02",
    "guessedTargetPath": "sfx/rail-scrape/rail-scrape-02.ogg",
    "importStatus": "candidate-only"
  },
  {
    "file": "sfx/rail-scrape/rail-scrape-03.ogg",
    "bytes": 29701,
    "probe": {
      "ok": true,
      "durationSeconds": 0.52,
      "sampleRate": 48000,
      "channels": 2
    },
    "guessedMatrixId": "sfx-railscrape-03",
    "guessedTargetPath": "sfx/rail-scrape/rail-scrape-03.ogg",
    "importStatus": "candidate-only"
  },
  {
    "file": "sfx/rail-scrape/rail-scrape-04.ogg",
    "bytes": 29882,
    "probe": {
      "ok": true,
      "durationSeconds": 0.52,
      "sampleRate": 48000,
      "channels": 2
    },
    "guessedMatrixId": "sfx-railscrape-04",
    "guessedTargetPath": "sfx/rail-scrape/rail-scrape-04.ogg",
    "importStatus": "candidate-only"
  },
  {
    "file": "sfx/rail-scrape/rail-scrape-05.ogg",
    "bytes": 29647,
    "probe": {
      "ok": true,
      "durationSeconds": 0.52,
      "sampleRate": 48000,
      "channels": 2
    },
    "guessedMatrixId": "sfx-railscrape-05",
    "guessedTargetPath": "sfx/rail-scrape/rail-scrape-05.ogg",
    "importStatus": "candidate-only"
  },
  {
    "file": "sfx/speed-pad/speed-pad-01.ogg",
    "bytes": 21680,
    "probe": {
      "ok": true,
      "durationSeconds": 0.72,
      "sampleRate": 48000,
      "channels": 2
    },
    "guessedMatrixId": "sfx-speedpad-01",
    "guessedTargetPath": "sfx/speed-pad/speed-pad-01.ogg",
    "importStatus": "candidate-only"
  },
  {
    "file": "sfx/speed-pad/speed-pad-02.ogg",
    "bytes": 21983,
    "probe": {
      "ok": true,
      "durationSeconds": 0.72,
      "sampleRate": 48000,
      "channels": 2
    },
    "guessedMatrixId": "sfx-speedpad-02",
    "guessedTargetPath": "sfx/speed-pad/speed-pad-02.ogg",
    "importStatus": "candidate-only"
  },
  {
    "file": "sfx/speed-pad/speed-pad-03.ogg",
    "bytes": 21937,
    "probe": {
      "ok": true,
      "durationSeconds": 0.72,
      "sampleRate": 48000,
      "channels": 2
    },
    "guessedMatrixId": "sfx-speedpad-03",
    "guessedTargetPath": "sfx/speed-pad/speed-pad-03.ogg",
    "importStatus": "candidate-only"
  },
  {
    "file": "sfx/speed-pad/speed-pad-04.ogg",
    "bytes": 22143,
    "probe": {
      "ok": true,
      "durationSeconds": 0.72,
      "sampleRate": 48000,
      "channels": 2
    },
    "guessedMatrixId": "sfx-speedpad-04",
    "guessedTargetPath": "sfx/speed-pad/speed-pad-04.ogg",
    "importStatus": "candidate-only"
  }
]